{
  "paper": "May 2023 P1H",
  "paperSlug": "May2023_P1H",
  "session": "May 2023",
  "code": "P1H",
  "isModular": false,
  "modularUnit": null,
  "questions": [
    {
      "id": "all::May2023_P1H__Q01__p03-03__m03__Ratio-Toolkit",
      "bank": "all",
      "q": 1,
      "marks": 3,
      "topic": "Ratio Toolkit",
      "unit": "Numbers & the Number System",
      "topicOrder": 11,
      "image": "/assets/questions/May2023_P1H__Q01__p03-03__m03__Ratio-Toolkit.png",
      "filename": "May2023_P1H__Q01__p03-03__m03__Ratio-Toolkit.png",
      "text": "1 Last season, the number of goals scored by Arjun, by Simon and by Kath for their football team were in the ratios 2 : 5 : 8 Simon scored 12 more goals than Arjun. Work out the number of goals scored by Kath. ....................................................... (Total for Question 1 is 3 marks)",
      "modularForceUnit": null
    },
    {
      "id": "all::May2023_P1H__Q02__p04-04__m03__Statistics-Toolkit",
      "bank": "all",
      "q": 2,
      "marks": 3,
      "topic": "Statistics Toolkit",
      "unit": "Statistics & Probability",
      "topicOrder": 52,
      "image": "/assets/questions/May2023_P1H__Q02__p04-04__m03__Statistics-Toolkit.png",
      "filename": "May2023_P1H__Q02__p04-04__m03__Statistics-Toolkit.png",
      "text": "2 The table gives information about the number of minutes that Abby spent walking each day in September. Number of minutes (M) Frequency 0 < M < 30 5 30 < M < 60 6 60 < M < 90 8 90 < M < 120 9 120 < M < 150 2 Work out an estimate for the total number of minutes that Abby spent walking in September. ....................................................... minutes (Total for Question 2 is 3 marks)",
      "modularForceUnit": null
    },
    {
      "id": "all::May2023_P1H__Q03__p05-05__m04__Percentages",
      "bank": "all",
      "q": 3,
      "marks": 4,
      "topic": "Percentages",
      "unit": "Numbers & the Number System",
      "topicOrder": 5,
      "image": "/assets/questions/May2023_P1H__Q03__p05-05__m04__Percentages.png",
      "filename": "May2023_P1H__Q03__p05-05__m04__Percentages.png",
      "text": "3 Nanette buys 60 notebooks for a total cost of 780 dirhams. Nanette sells 70% of the notebooks for 22 dirhams each. She sells the remaining notebooks for 19 dirhams each. Work out Nanette’s percentage profit. Give your answer correct to 3 significant figures. .......................................................% (Total for Question 3 is 4 marks)",
      "modularForceUnit": null
    },
    {
      "id": "all::May2023_P1H__Q04__p06-07__m08__Transformations",
      "bank": "all",
      "q": 4,
      "marks": 8,
      "topic": "Transformations",
      "unit": "Vectors & Transformation Geometry",
      "topicOrder": 51,
      "image": "/assets/questions/May2023_P1H__Q04__p06-07__m08__Transformations.png",
      "filename": "May2023_P1H__Q04__p06-07__m08__Transformations.png",
      "text": "4 The diagram shows a sketch of triangle A and triangle B on a coordinate grid. B A (6, 12) (2, d) (9, e) (-7, 2) (-11, -5) ( f, -3) y x O Diagram NOT accurately drawn (a) Given that triangle A has been translated to give triangle B, work out the value of d, the value of e and the value of f d = ....................................................... e = ....................................................... f = ....................................................... (3) The diagram shows shape P and shape Q drawn on a grid. 12 11 10 9 8 7 6 5 4 3 2 1 O 12 11 10 9 8 7 6 5 4 3 2 1 y x P Q (b) Describe fully the single transformation that maps shape P onto shape Q .................................................................................................................................................................................................................................................. .................................................................................................................................................................................................................................................. (3) (c) On the grid above, rotate shape P 90° clockwise about (3, 5) Label your shape R (2) (Total for Question 4 is 8 marks)",
      "modularForceUnit": null
    },
    {
      "id": "all::May2023_P1H__Q05__p08-08__m04__Right-Angled-Triangles-Pythagoras-and-Trigonometry",
      "bank": "all",
      "q": 5,
      "marks": 4,
      "topic": "Right-Angled Triangles - Pythagoras & Trigonometry",
      "unit": "Geometry & Trigonometry",
      "topicOrder": 47,
      "image": "/assets/questions/May2023_P1H__Q05__p08-08__m04__Right-Angled-Triangles-Pythagoras-and-Trigonometry.png",
      "filename": "May2023_P1H__Q05__p08-08__m04__Right-Angled-Triangles-Pythagoras-and-Trigonometry.png",
      "text": "5 The diagram shows a shaded shape AEBCD made by removing triangle AEB from rectangle ABCD A D B C E 7.2 cm 5.4 cm 6 cm Diagram NOT accurately drawn AE = 7.2 cm BE = 5.4 cm BC = 6 cm angle AEB = 90° Work out the perimeter of the shaded shape. ....................................................... cm (Total for Question 5 is 4 marks)",
      "modularForceUnit": null
    },
    {
      "id": "all::May2023_P1H__Q06__p09-09__m08__Factorising",
      "bank": "all",
      "q": 6,
      "marks": 8,
      "topic": "Factorising",
      "unit": "Equations, Formulae & Identities",
      "topicOrder": 18,
      "image": "/assets/questions/May2023_P1H__Q06__p09-09__m08__Factorising.png",
      "filename": "May2023_P1H__Q06__p09-09__m08__Factorising.png",
      "text": "6 (a) Simplify (2c 4 d 7) 3 ....................................................... (2) (b) Find the value of 5y 0 where y > 0 ....................................................... (1) (c) Factorise fully 16a 2b 3 + 20a 3b ....................................................... (2) (d) (i) Factorise x 2 + 9x - 22 ....................................................... (2) (ii) Hence solve x 2 + 9x - 22 = 0 ....................................................... (1) (Total for Question 6 is 8 marks)",
      "modularForceUnit": null
    },
    {
      "id": "all::May2023_P1H__Q07__p10-10__m04__Graphing-Inequalities",
      "bank": "all",
      "q": 7,
      "marks": 4,
      "topic": "Graphing Inequalities",
      "unit": "Sequences, Functions & Graphs",
      "topicOrder": 35,
      "image": "/assets/questions/May2023_P1H__Q07__p10-10__m04__Graphing-Inequalities.png",
      "filename": "May2023_P1H__Q07__p10-10__m04__Graphing-Inequalities.png",
      "text": "7 y x -4 -3 -2 -1 O 1 2 3 4 -3 -2 -1 1 2 3 4 5 6 7 8 R 9 5 The region R, shown shaded in the diagram, is bounded by three straight lines. Find the inequalities that define R ....................................................... ....................................................... ....................................................... (Total for Question 7 is 4 marks)",
      "modularForceUnit": null
    },
    {
      "id": "all::May2023_P1H__Q08__p11-11__m04__Prime-Factors-HCF-and-LCM",
      "bank": "all",
      "q": 8,
      "marks": 4,
      "topic": "Prime Factors, HCF & LCM",
      "unit": "Numbers & the Number System",
      "topicOrder": 2,
      "image": "/assets/questions/May2023_P1H__Q08__p11-11__m04__Prime-Factors-HCF-and-LCM.png",
      "filename": "May2023_P1H__Q08__p11-11__m04__Prime-Factors-HCF-and-LCM.png",
      "text": "8 (a) Write 300 as a product of its prime factors. Show your working clearly. ....................................................... (2) A = 2 × 2 × 2 × 3 × 3 × 5 B = 2 × 2 × 3 × 3 × 3 × 5 (b) Find the lowest common multiple (LCM) of 5A and 7B Show your working clearly. ....................................................... (2) (Total for Question 8 is 4 marks)",
      "modularForceUnit": null
    },
    {
      "id": "all::May2023_P1H__Q09__p12-12__m03__Simultaneous-Equations",
      "bank": "all",
      "q": 9,
      "marks": 3,
      "topic": "Simultaneous Equations",
      "unit": "Equations, Formulae & Identities",
      "topicOrder": 26,
      "image": "/assets/questions/May2023_P1H__Q09__p12-12__m03__Simultaneous-Equations.png",
      "filename": "May2023_P1H__Q09__p12-12__m03__Simultaneous-Equations.png",
      "text": "9 Solve the simultaneous equations 2x + 9y = 14.5 7x + 3y = 8 Show clear algebraic working. x = ....................................................... y = ....................................................... (Total for Question 9 is 3 marks)",
      "modularForceUnit": null
    },
    {
      "id": "all::May2023_P1H__Q10__p12-12__m02__Statistics-Toolkit",
      "bank": "all",
      "q": 10,
      "marks": 2,
      "topic": "Statistics Toolkit",
      "unit": "Statistics & Probability",
      "topicOrder": 52,
      "image": "/assets/questions/May2023_P1H__Q10__p12-12__m02__Statistics-Toolkit.png",
      "filename": "May2023_P1H__Q10__p12-12__m02__Statistics-Toolkit.png",
      "text": "10 Here are the test marks of 15 students. 7 10 14 15 16 17 18 19 20 20 23 25 30 39 40 Find the interquartile range of these marks. ....................................................... (Total for Question 10 is 2 marks)",
      "modularForceUnit": null
    },
    {
      "id": "all::May2023_P1H__Q11__p13-13__m06__Differentiation",
      "bank": "all",
      "q": 11,
      "marks": 6,
      "topic": "Differentiation",
      "unit": "Sequences, Functions & Graphs",
      "topicOrder": 37,
      "image": "/assets/questions/May2023_P1H__Q11__p13-13__m06__Differentiation.png",
      "filename": "May2023_P1H__Q11__p13-13__m06__Differentiation.png",
      "text": "11 The curve C has equation y = 4x 3 + x 2 - 20x (a) Find d d y x d d y x = ....................................................... (2) (b) Find the x coordinates of the points on C where the gradient is 4 Show clear algebraic working. ....................................................... (4) (Total for Question 11 is 6 marks)",
      "modularForceUnit": null
    },
    {
      "id": "all::May2023_P1H__Q12__p14-14__m04__Cumulative-Frequency-Diagrams",
      "bank": "all",
      "q": 12,
      "marks": 4,
      "topic": "Cumulative Frequency Diagrams",
      "unit": "Statistics & Probability",
      "topicOrder": 54,
      "image": "/assets/questions/May2023_P1H__Q12__p14-14__m04__Cumulative-Frequency-Diagrams.png",
      "filename": "May2023_P1H__Q12__p14-14__m04__Cumulative-Frequency-Diagrams.png",
      "text": "12 The cumulative frequency graph shows information about the heights, in centimetres, of 50 plants in a flowerbed. 60 50 40 30 20 10 O 50 40 30 20 10 Height (centimetres) Cumulative frequency (a) Use the graph to find an estimate for the median height of these plants. ....................................................... centimetres (1) (b) Use the graph to find the frequency for the class interval 30 < Height < 40 ....................................................... (1) (c) Use the graph to find an estimate for the number of plants with a height greater than 35 centimetres. ....................................................... (2) (Total for Question 12 is 4 marks)",
      "modularForceUnit": null
    },
    {
      "id": "all::May2023_P1H__Q13__p15-15__m03__Coordinate-Geometry",
      "bank": "all",
      "q": 13,
      "marks": 3,
      "topic": "Coordinate Geometry",
      "unit": "Sequences, Functions & Graphs",
      "topicOrder": 30,
      "image": "/assets/questions/May2023_P1H__Q13__p15-15__m03__Coordinate-Geometry.png",
      "filename": "May2023_P1H__Q13__p15-15__m03__Coordinate-Geometry.png",
      "text": "13 A is the point with coordinates (-5, 12) B is the point with coordinates (19, -48) Find an equation of the straight line that passes through the points A and B ....................................................... (Total for Question 13 is 3 marks)",
      "modularForceUnit": null
    },
    {
      "id": "all::May2023_P1H__Q14__p15-15__m03__Factorising",
      "bank": "all",
      "q": 14,
      "marks": 3,
      "topic": "Factorising",
      "unit": "Equations, Formulae & Identities",
      "topicOrder": 18,
      "image": "/assets/questions/May2023_P1H__Q14__p15-15__m03__Factorising.png",
      "filename": "May2023_P1H__Q14__p15-15__m03__Factorising.png",
      "text": "14 Factorise fully 50g 2 - 18 ....................................................... (Total for Question 14 is 3 marks)",
      "modularForceUnit": null
    },
    {
      "id": "all::May2023_P1H__Q15__p16-16__m06__Powers-Roots-and-Standard-Form",
      "bank": "all",
      "q": 15,
      "marks": 6,
      "topic": "Powers, Roots & Standard Form",
      "unit": "Numbers & the Number System",
      "topicOrder": 3,
      "image": "/assets/questions/May2023_P1H__Q15__p16-16__m06__Powers-Roots-and-Standard-Form.png",
      "filename": "May2023_P1H__Q15__p16-16__m06__Powers-Roots-and-Standard-Form.png",
      "text": "15 (a) 2 8 16 2 3 3 2 n Work out the value of n Show your working clearly. n = ....................................................... (3) (b) Find 4% of 4.5 × 10 157 Give your answer in standard form. ....................................................... (3) (Total for Question 15 is 6 marks)",
      "modularForceUnit": null
    },
    {
      "id": "all::May2023_P1H__Q16__p17-17__m03__Set-Notation-and-Venn-Diagrams",
      "bank": "all",
      "q": 16,
      "marks": 3,
      "topic": "Set Notation & Venn Diagrams",
      "unit": "Numbers & the Number System",
      "topicOrder": 1,
      "image": "/assets/questions/May2023_P1H__Q16__p17-17__m03__Set-Notation-and-Venn-Diagrams.png",
      "filename": "May2023_P1H__Q16__p17-17__m03__Set-Notation-and-Venn-Diagrams.png",
      "text": "16 The Venn diagram shows a universal set E and sets A, B and C The numbers and the letter x represent numbers of elements. A B C E 9 10 7 7 12 x 3 5 Given that n(A ∪ B) = 42 (a) find the value of x x = ....................................................... (1) (b) Find n(Aʹ) ....................................................... (1) (c) Find n(Bʹ ∩ C) ....................................................... (1) (Total for Question 16 is 3 marks)",
      "modularForceUnit": null
    },
    {
      "id": "all::May2023_P1H__Q17__p18-18__m04__Functions",
      "bank": "all",
      "q": 17,
      "marks": 4,
      "topic": "Functions",
      "unit": "Sequences, Functions & Graphs",
      "topicOrder": 29,
      "image": "/assets/questions/May2023_P1H__Q17__p18-18__m04__Functions.png",
      "filename": "May2023_P1H__Q17__p18-18__m04__Functions.png",
      "text": "17 The functions g and h are such that g(x) = 11 2 5 x - h(x) = x 2 + 4 x  0 (a) What value of x must be excluded from any domain of g? ....................................................... (1) (b) Solve gh(x) = 1 ....................................................... (3) (Total for Question 17 is 4 marks)",
      "modularForceUnit": null
    },
    {
      "id": "all::May2023_P1H__Q18__p19-19__m04__Histograms",
      "bank": "all",
      "q": 18,
      "marks": 4,
      "topic": "Histograms",
      "unit": "Statistics & Probability",
      "topicOrder": 53,
      "image": "/assets/questions/May2023_P1H__Q18__p19-19__m04__Histograms.png",
      "filename": "May2023_P1H__Q18__p19-19__m04__Histograms.png",
      "text": "18 The incomplete table and incomplete histogram give information about the times, in minutes, that 140 people waited at a station for a train. Time (t minutes) Frequency 0 < t < 5 23 5 < t < 15 15 < t < 30 30 < t < 40 18 40 < t < 60 14 60 50 40 30 20 10 0 0 Time (t minutes) Frequency density Complete the table and the histogram. (Total for Question 18 is 4 marks)",
      "modularForceUnit": null
    },
    {
      "id": "all::May2023_P1H__Q19__p20-21__m05__Vectors",
      "bank": "all",
      "q": 19,
      "marks": 5,
      "topic": "Vectors",
      "unit": "Vectors & Transformation Geometry",
      "topicOrder": 50,
      "image": "/assets/questions/May2023_P1H__Q19__p20-21__m05__Vectors.png",
      "filename": "May2023_P1H__Q19__p20-21__m05__Vectors.png",
      "text": "19 A B N O P M a b Diagram NOT accurately drawn OMA, ONB, MPB and NPA are straight lines. M is the midpoint of OA ON : NB = 1 : 5 OM → = a ON → = b (a) Find in terms of a and b the vector AN → ....................................................... (1) (b) Use a vector method to find the ratio AP : PN AP : PN = ....................................................... (4) (Total for Question 19 is 5 marks)",
      "modularForceUnit": null
    },
    {
      "id": "all::May2023_P1H__Q20__p22-23__m06__Sequences",
      "bank": "all",
      "q": 20,
      "marks": 6,
      "topic": "Sequences",
      "unit": "Sequences, Functions & Graphs",
      "topicOrder": 28,
      "image": "/assets/questions/May2023_P1H__Q20__p22-23__m06__Sequences.png",
      "filename": "May2023_P1H__Q20__p22-23__m06__Sequences.png",
      "text": "20 The sum of the first 80 terms of an arithmetic series, S, is 470 The 75th term of S is 14.5 The sum of the first X terms of S is 171 Work out the value of X Show your working clearly. X = ....................................................... (Total for Question 20 is 6 marks)",
      "modularForceUnit": null
    },
    {
      "id": "expertise::May2023_P1H__Q20__p22-23__m06__Sequences",
      "bank": "expertise",
      "q": 20,
      "marks": 6,
      "topic": "Sequences",
      "unit": "Sequences, Functions & Graphs",
      "topicOrder": 28,
      "image": "/assets/questions/May2023_P1H__Q20__p22-23__m06__Sequences.png",
      "filename": "May2023_P1H__Q20__p22-23__m06__Sequences.png",
      "text": "20 The sum of the first 80 terms of an arithmetic series, S, is 470 The 75th term of S is 14.5 The sum of the first X terms of S is 171 Work out the value of X Show your working clearly. X = ....................................................... (Total for Question 20 is 6 marks)",
      "modularForceUnit": null
    },
    {
      "id": "all::May2023_P1H__Q21__p23-23__m02__Transformations-of-Graphs",
      "bank": "all",
      "q": 21,
      "marks": 2,
      "topic": "Transformations of Graphs",
      "unit": "Sequences, Functions & Graphs",
      "topicOrder": 36,
      "image": "/assets/questions/May2023_P1H__Q21__p23-23__m02__Transformations-of-Graphs.png",
      "filename": "May2023_P1H__Q21__p23-23__m02__Transformations-of-Graphs.png",
      "text": "21 A curve has equation y = f(x) There is only one turning point on the curve. The coordinates of this turning point are (6, 5) Write down the coordinates of the turning point on the curve with equation (a) y = f(x - 4) (............................ , ............................) (1) (b) y = f(3x) (............................ , ............................) (1) (Total for Question 21 is 2 marks)",
      "modularForceUnit": null
    },
    {
      "id": "expertise::May2023_P1H__Q21__p23-23__m02__Transformations-of-Graphs",
      "bank": "expertise",
      "q": 21,
      "marks": 2,
      "topic": "Transformations of Graphs",
      "unit": "Sequences, Functions & Graphs",
      "topicOrder": 36,
      "image": "/assets/questions/May2023_P1H__Q21__p23-23__m02__Transformations-of-Graphs.png",
      "filename": "May2023_P1H__Q21__p23-23__m02__Transformations-of-Graphs.png",
      "text": "21 A curve has equation y = f(x) There is only one turning point on the curve. The coordinates of this turning point are (6, 5) Write down the coordinates of the turning point on the curve with equation (a) y = f(x - 4) (............................ , ............................) (1) (b) y = f(3x) (............................ , ............................) (1) (Total for Question 21 is 2 marks)",
      "modularForceUnit": null
    },
    {
      "id": "all::May2023_P1H__Q22__p24-25__m06__Circles-Arcs-and-Sectors",
      "bank": "all",
      "q": 22,
      "marks": 6,
      "topic": "Circles, Arcs & Sectors",
      "unit": "Geometry & Trigonometry",
      "topicOrder": 43,
      "image": "/assets/questions/May2023_P1H__Q22__p24-25__m06__Circles-Arcs-and-Sectors.png",
      "filename": "May2023_P1H__Q22__p24-25__m06__Circles-Arcs-and-Sectors.png",
      "text": "22 The diagram shows two circles with centre O and a regular pentagon ABCDE A B C D E O Diagram NOT accurately drawn A, B, C, D and E are points on the larger circle. The pentagon has sides of length 8 cm. The diagram is shaded such that shaded area = unshaded area Work out the radius of the smaller circle. Give your answer correct to 3 significant figures. ....................................................... cm (Total for Question 22 is 6 marks)",
      "modularForceUnit": null
    },
    {
      "id": "expertise::May2023_P1H__Q22__p24-25__m06__Circles-Arcs-and-Sectors",
      "bank": "expertise",
      "q": 22,
      "marks": 6,
      "topic": "Circles, Arcs & Sectors",
      "unit": "Geometry & Trigonometry",
      "topicOrder": 43,
      "image": "/assets/questions/May2023_P1H__Q22__p24-25__m06__Circles-Arcs-and-Sectors.png",
      "filename": "May2023_P1H__Q22__p24-25__m06__Circles-Arcs-and-Sectors.png",
      "text": "22 The diagram shows two circles with centre O and a regular pentagon ABCDE A B C D E O Diagram NOT accurately drawn A, B, C, D and E are points on the larger circle. The pentagon has sides of length 8 cm. The diagram is shaded such that shaded area = unshaded area Work out the radius of the smaller circle. Give your answer correct to 3 significant figures. ....................................................... cm (Total for Question 22 is 6 marks)",
      "modularForceUnit": null
    },
    {
      "id": "all::May2023_P1H__Q23__p26-27__m05__Area-and-Volume-of-Similar-Shapes",
      "bank": "all",
      "q": 23,
      "marks": 5,
      "topic": "Area & Volume of Similar Shapes",
      "unit": "Geometry & Trigonometry",
      "topicOrder": 46,
      "image": "/assets/questions/May2023_P1H__Q23__p26-27__m05__Area-and-Volume-of-Similar-Shapes.png",
      "filename": "May2023_P1H__Q23__p26-27__m05__Area-and-Volume-of-Similar-Shapes.png",
      "text": "23 A frustum is made by removing a small square-based pyramid from a similar large squared‐based pyramid as shown in the diagram. Diagram NOT accurately drawn 15 cm 39 cm 39 cm 45 cm The height of the small pyramid is 15 cm. The height of the large pyramid is 45 cm. The square base of the large pyramid has side length 39 cm. Work out the total surface area of the frustum. Give your answer correct to the nearest whole number. ....................................................... cm 2 (Total for Question 23 is 5 marks)",
      "modularForceUnit": null
    },
    {
      "id": "expertise::May2023_P1H__Q23__p26-27__m05__Area-and-Volume-of-Similar-Shapes",
      "bank": "expertise",
      "q": 23,
      "marks": 5,
      "topic": "Area & Volume of Similar Shapes",
      "unit": "Geometry & Trigonometry",
      "topicOrder": 46,
      "image": "/assets/questions/May2023_P1H__Q23__p26-27__m05__Area-and-Volume-of-Similar-Shapes.png",
      "filename": "May2023_P1H__Q23__p26-27__m05__Area-and-Volume-of-Similar-Shapes.png",
      "text": "23 A frustum is made by removing a small square-based pyramid from a similar large squared‐based pyramid as shown in the diagram. Diagram NOT accurately drawn 15 cm 39 cm 39 cm 45 cm The height of the small pyramid is 15 cm. The height of the large pyramid is 45 cm. The square base of the large pyramid has side length 39 cm. Work out the total surface area of the frustum. Give your answer correct to the nearest whole number. ....................................................... cm 2 (Total for Question 23 is 5 marks)",
      "modularForceUnit": null
    }
  ],
  "questionCount": 27
}